ivlam-0.1.10.dist-info/RECORD
ivlam-0.1.10.dist-info/WHEEL
ivlam-0.1.10.dist-info/METADATA
ivlam/ivLamTree_20210202_160219_i2d8.bin
ivlam/_ivlam.cpython-311-i386-linux-gnu.so
ivlam/__init__.py
ivlam/ivlam.py
ivlam.libs/libgfortran-a8535147.so.5.0.0
ivlam.libs/libquadmath-e2ac3af2.so.0.0.0
