Metadata-Version: 2.1
Name: ivlam
Version: 0.1.10
Summary: A Python wrapper for ivlam
Author-Email: pennbay <pennbay@outlook.com>
License: GNU General Public License v3 or later (GPLv3+)
Classifier: Programming Language :: Python :: 3
Classifier: License :: OSI Approved :: GNU General Public License v3 or later (GPLv3+)
Project-URL: Repository, https://github.com/pennbay/ivlam.git
Project-URL: Bug tracker, https://github.com/pennbay/ivlam/issues
Requires-Python: >=3.8
